nameof/__init__.py
nameof/nameof.py
python_nameof-2.0.2.dist-info/licenses/LICENSE
python_nameof-2.0.2.dist-info/METADATA
python_nameof-2.0.2.dist-info/WHEEL
python_nameof-2.0.2.dist-info/top_level.txt
python_nameof-2.0.2.dist-info/RECORD
