Metadata-Version: 2.4
Name: python_nameof
Version: 2.0.2
Summary: A Python implementation of the C# nameof operator.
Author-email: Alessio Lombardi <work@alelom.com>
License: MIT License
Project-URL: Homepage, https://github.com/alelom/python_nameof
Classifier: Programming Language :: Python :: 3
Classifier: License :: OSI Approved :: MIT License
Classifier: Operating System :: OS Independent
Requires-Python: >=3.7
License-File: LICENSE
Dynamic: license-file
